fastapi_authlib_oidc-1.0.2.dist-info/licenses/LICENSE
fastapi_oidc/__init__.py
fastapi_oidc/app.py
fastapi_oidc/authlib.py
fastapi_oidc/client.py
fastapi_oidc/user.py
fastapi_authlib_oidc-1.0.2.dist-info/METADATA
fastapi_authlib_oidc-1.0.2.dist-info/WHEEL
fastapi_authlib_oidc-1.0.2.dist-info/top_level.txt
fastapi_authlib_oidc-1.0.2.dist-info/RECORD
