Metadata-Version: 2.4
Name: fastapi-authlib-oidc
Version: 1.0.2
Summary: FastAPI authlib OpenID integration
Author-email: Frédérick NEY <frederick.ney@gmail.com>
License:                     GNU GENERAL PUBLIC LICENSE
Project-URL: Homepage, https://github.com/frederickney/fastapi-authlib-oidc
Project-URL: Documentation, https://github.com/frederickney/fastapi-authlib-oidc/blob/master/README.md
Project-URL: Repository, https://github.com/frederickney/fastapi-authlib-oidc
Project-URL: Issues, https://github.com/frederickney/fastapi-authlib-oidc/issues
Project-URL: source, https://github.com/frederickney/fastapi-authlib-oidc
Classifier: Environment :: Web Environment
Classifier: Intended Audience :: Developers
Classifier: Operating System :: OS Independent
Classifier: Framework :: FastAPI
Classifier: Topic :: Software Development :: Libraries :: Python Modules
Classifier: Programming Language :: Python :: 3.7
Classifier: Programming Language :: Python :: 3.8
Classifier: Programming Language :: Python :: 3.9
Classifier: Programming Language :: Python :: 3.10
Classifier: Programming Language :: Python :: 3.11
Classifier: Programming Language :: Python :: 3.12
Classifier: Programming Language :: Python :: 3.13
Requires-Python: >=3.7
License-File: LICENSE
Requires-Dist: werkzeug
Requires-Dist: authlib
Requires-Dist: requests
Requires-Dist: FastAPI
Requires-Dist: importlib-metadata; python_version > "3.7"
Dynamic: license-file
